minisign/__init__.py
minisign/__main__.py
minisign/tests/__init__.py
minisign-0.1.0.dist-info/entry_points.txt
minisign-0.1.0.dist-info/LICENSE
minisign-0.1.0.dist-info/WHEEL
minisign-0.1.0.dist-info/METADATA
minisign-0.1.0.dist-info/RECORD
