Metadata-Version: 2.1
Name: minisign
Version: 0.1.0
Summary: A dead simple tool to sign files and verify signatures
Home-page: https://gitlab.com/hackancuba/minisign-py
License: MPL-2.0
Author: HacKan
Author-email: hackan@gmail.com
Requires-Python: >=3.7,<4.0
Classifier: Development Status :: 1 - Planning
Classifier: Environment :: Console
Classifier: Intended Audience :: Developers
Classifier: Intended Audience :: End Users/Desktop
Classifier: Intended Audience :: Information Technology
Classifier: Intended Audience :: System Administrators
Classifier: License :: OSI Approved
Classifier: License :: OSI Approved :: Mozilla Public License 2.0 (MPL 2.0)
Classifier: Natural Language :: English
Classifier: Operating System :: POSIX :: Linux
Classifier: Programming Language :: Python :: 3
Classifier: Programming Language :: Python :: 3 :: Only
Classifier: Programming Language :: Python :: 3.7
Classifier: Programming Language :: Python :: 3.8
Classifier: Topic :: Security :: Cryptography
Classifier: Typing :: Typed
Project-URL: Repository, https://gitlab.com/hackancuba/minisign-py
